podop/__init__.py
podop/dovecot.py
podop/postfix.py
podop/table.py
podop-0.2.6.data/scripts/podop
podop-0.2.6.dist-info/LICENSE.md
podop-0.2.6.dist-info/METADATA
podop-0.2.6.dist-info/WHEEL
podop-0.2.6.dist-info/top_level.txt
podop-0.2.6.dist-info/RECORD
