Metadata-Version: 2.1
Name: podop
Version: 0.2.6
Summary: Postfix and Dovecot proxy
Home-page: https://github.com/mailu/podop.git
Author: Pierre Jaury
Author-email: pierre@jaury.eu
License: UNKNOWN
Platform: UNKNOWN
Requires-Dist: aiohttp
